chainsail_helpers/__init__.py
chainsail_helpers/pdf/__init__.py
chainsail_helpers/pdf/pymc/__init__.py
chainsail_helpers/pdf/stan/#__init__.py#
chainsail_helpers/pdf/stan/__init__.py
chainsail_helpers/scripts/README.md
chainsail_helpers/scripts/__init__.py
chainsail_helpers/scripts/concatenate_samples.py
chainsail_helpers-0.1.5.1.dist-info/entry_points.txt
chainsail_helpers-0.1.5.1.dist-info/WHEEL
chainsail_helpers-0.1.5.1.dist-info/METADATA
chainsail_helpers-0.1.5.1.dist-info/RECORD
