Metadata-Version: 2.1
Name: chainsail-helpers
Version: 0.1.5.1
Summary: Probability distribution interfaces, examples, and utilities for the Chainsail sampling service
Home-page: https://github.com/tweag/chainsail-resources
License: MIT
Keywords: probabilistic programming,sampling,MCMC
Author: Simeon Carstens
Author-email: simeon.carstens@tweag.io
Requires-Python: >=3.8
Classifier: License :: OSI Approved :: MIT License
Classifier: Programming Language :: Python :: 3
Classifier: Programming Language :: Python :: 3.8
Classifier: Programming Language :: Python :: 3.9
Classifier: Programming Language :: Python :: 3.10
Classifier: Programming Language :: Python :: 3.11
Provides-Extra: pymc
Provides-Extra: stan
Requires-Dist: numpy (>=1.21.2,<2.0.0)
Requires-Dist: pymc (>=4.1.4,<5.0.0); extra == "pymc"
Requires-Dist: requests (>=2.26.0,<3.0.0); extra == "stan"
Project-URL: Repository, https://github.com/tweag/chainsail-resources
